tensorsat/__init__.py
tensorsat/_autoray.py
tensorsat/diagrams.py
tensorsat/py.typed
tensorsat/_utils/__init__.py
tensorsat/_utils/meta.py
tensorsat/_utils/misc.py
tensorsat/contractions/__init__.py
tensorsat/contractions/abc.py
tensorsat/contractions/cotengra.py
tensorsat/contractions/simple.py
tensorsat/lang/__init__.py
tensorsat/lang/fin_rel.py
tensorsat/lib/__init__.py
tensorsat/lib/bincirc.py
tensorsat/lib/sat.py
tensorsat/viz/__init__.py
tensorsat/viz/diagrams.py
tensorsat-0.1.0.dist-info/LICENSE
tensorsat-0.1.0.dist-info/METADATA
tensorsat-0.1.0.dist-info/WHEEL
tensorsat-0.1.0.dist-info/top_level.txt
tensorsat-0.1.0.dist-info/RECORD
