Metadata-Version: 2.2
Name: tensorsat
Version: 0.1.0
Summary: A SAT solver based on relational network contraction.
Author: Hashberg
Project-URL: Documentation, https://tensorsat.readthedocs.io
Project-URL: Repository, https://github.com/hashberg-io/tensorsat
Project-URL: Issues, https://github.com/hashberg-io/tensorsat/issues
Classifier: Programming Language :: Python :: 3
Classifier: Operating System :: OS Independent
Classifier: Development Status :: 2 - Pre-Alpha
Classifier: Programming Language :: Python :: 3.13
Classifier: Natural Language :: English
Classifier: Typing :: Typed
Requires-Python: >=3.13
License-File: LICENSE
Requires-Dist: numpy==2.1.3
Requires-Dist: hashcons>=0.1.0
Requires-Dist: typing-validation>=1.2.11
Requires-Dist: xxhash>=3.5.0
Requires-Dist: opt_einsum>=3.4.0
